{
    "/app.js": "/app.js",
    "/app.7419abc4a5d0e32500f0.hot-update.js": "/app.7419abc4a5d0e32500f0.hot-update.js",
    "/app.9572ea6055a7be184fe4.hot-update.js": "/app.9572ea6055a7be184fe4.hot-update.js",
    "/app.16059e136c0626b787df.hot-update.js": "/app.16059e136c0626b787df.hot-update.js",
    "/app.9794dc4ffbb9b2b60db8.hot-update.js": "/app.9794dc4ffbb9b2b60db8.hot-update.js",
    "/app.dd988bd8ea6bb542a4a6.hot-update.js": "/app.dd988bd8ea6bb542a4a6.hot-update.js",
    "/app.e46ee3c654eadf50d1da.hot-update.js": "/app.e46ee3c654eadf50d1da.hot-update.js",
    "/app.34258509059456fb78ba.hot-update.js": "/app.34258509059456fb78ba.hot-update.js",
    "/app.f88591c11ea94023d4ae.hot-update.js": "/app.f88591c11ea94023d4ae.hot-update.js",
    "/app.b1d9be8ef534c91a2cd4.hot-update.js": "/app.b1d9be8ef534c91a2cd4.hot-update.js",
    "/app.8ca2b8e911d408fecbd4.hot-update.js": "/app.8ca2b8e911d408fecbd4.hot-update.js",
    "/app.0fde23baae73b90cfb34.hot-update.js": "/app.0fde23baae73b90cfb34.hot-update.js",
    "/app.849a6be478c644a800d3.hot-update.js": "/app.849a6be478c644a800d3.hot-update.js"
}
